deoverlap/__init__.py
deoverlap/deoverlap.py
deoverlap-2.0.1.dist-info/licenses/LICENSE
deoverlap-2.0.1.dist-info/METADATA
deoverlap-2.0.1.dist-info/WHEEL
deoverlap-2.0.1.dist-info/top_level.txt
deoverlap-2.0.1.dist-info/RECORD
