Metadata-Version: 2.4
Name: deoverlap
Version: 2.0.1
Summary: A high-level toolkit for de-overlapping Shapely geometries.
Author-email: Pietro Leoni <pietro.leoni@gmail.com>
License: MIT License
Project-URL: Homepage, https://github.com/piLeoni/deoverlap
Project-URL: Bug Tracker, https://github.com/piLeoni/deoverlap
Classifier: Programming Language :: Python :: 3
Classifier: Programming Language :: Python :: 3.10
Classifier: Programming Language :: Python :: 3.11
Classifier: Programming Language :: Python :: 3.12
Classifier: License :: OSI Approved :: MIT License
Classifier: Operating System :: OS Independent
Classifier: Topic :: Scientific/Engineering :: GIS
Classifier: Topic :: Utilities
Requires-Python: >=3.10
License-File: LICENSE
Requires-Dist: shapely>=2.0
Requires-Dist: tqdm
Provides-Extra: test
Requires-Dist: pytest; extra == "test"
Requires-Dist: matplotlib; extra == "test"
Dynamic: license-file
